MANIFEST.in
README.md
setup.py
ploev/__init__.py
ploev/calc.py
ploev/cards.py
ploev/easy_range.py
ploev/game.py
ploev/ploev.ini
ploev/ppt.py
ploev/ranges.json
ploev/ranges.py
ploev/settings.py
ploev.egg-info/PKG-INFO
ploev.egg-info/SOURCES.txt
ploev.egg-info/dependency_links.txt
ploev.egg-info/not-zip-safe
ploev.egg-info/requires.txt
ploev.egg-info/top_level.txt